[
    {
        "summary": "Sofia, the capital city of Bulgaria, is known for its mix of ancient and modern attractions, including 2000-year-old churches, municipal buildings, cathedrals, modern museums, art galleries, city parks, and boulevards. Notable sites include Boyana Church, Alexander Nevsky Cathedral, Ivan Vazov National Theatre, Saint Nedelja Church, and the National Museum of Military History and South Park.",
        "questions": [
            {
                "question": "What is the name of this attraction?",
                "answer": "Sofia"
            },
            {
                "question": "What are the opening hours of this attraction?",
                "answer": "Not mentioned"
            },
            {
                "question": "What is the entry fees of this attraction?",
                "answer": "Not mentioned"
            }
        ]
    },
    {
        "summary": "Varna, a serene resort town overlooking the Black Sea, is known for its historical and cultural sites, including Roman baths, ancient cathedrals, and museums. The vibrant beaches lined with shacks and bars are popular for sunbathing, unwinding, and water sports. Key attractions include the Roman Bath, Dormition of the Mother of God Cathedral, Baroque Opera House, and Cathedral of the Assumption of the Virgin.",
        "questions": [
            {
                "question": "What is the name of this attraction?",
                "answer": "Varna"
            },
            {
                "question": "What are the opening hours of this attraction?",
                "answer": "Not mentioned"
            },
            {
                "question": "What is the entry fees of this attraction?",
                "answer": "Not mentioned"
            }
        ]
    },
    {
        "summary": "Plovdiv, one of the historical cities in Bulgaria, is built around 7 hills along the Maritsa River. It features fortresses, amphitheaters, churches, cobblestone roads, and vintage houses. This city is a popular destination for history lovers and anthropologists. Key attractions include the Plovdiv Roman Stadium, Roman Amphitheater, Staria Grad, Park Tsar Simeon, Alyosha Soviet Army Memorial, and Ethnographic Museum.",
        "questions": [
            {
                "question": "What is the name of this attraction?",
                "answer": "Plovdiv"
            },
            {
                "question": "What are the opening hours of this attraction?",
                "answer": "Not mentioned"
            },
            {
                "question": "What is the entry fees of this attraction?",
                "answer": "Not mentioned"
            }
        ]
    },
    {
        "summary": "Rila Monastery, located in the Rila Mountains, is the largest monastery in Bulgaria and a UNESCO World Heritage Site. It is known for its stunning architecture, including wooden staircases, black and white arches, domes, and colorful mosaics. Visitors can also explore Rila National Park, Rila Mountains, and Medi Valley Winery. The monastery houses 250 manuscripts and paintings.",
        "questions": [
            {
                "question": "What is the name of this attraction?",
                "answer": "Rila Monastery"
            },
            {
                "question": "What are the opening hours of this attraction?",
                "answer": "Not mentioned"
            },
            {
                "question": "What is the entry fees of this attraction?",
                "answer": "Not mentioned"
            }
        ]
    },
    {
        "summary": "Nesebar, located by the Black Sea coast, is known for its ancient ruins, edifices, and stunning beaches. The old part of Nesebar, with its fortifications and Roman baths, is on an island connected to the mainland by a walkway. Visitors can explore the 11th-century St. Stephen Church, known for its ornamented altarpiece and mural paintings. Activities include sunbathing, water sports, and visiting the beachfront water park.",
        "questions": [
            {
                "question": "What is the name of this attraction?",
                "answer": "Nesebar"
            },
            {
                "question": "What are the opening hours of this attraction?",
                "answer": "Not mentioned"
            },
            {
                "question": "What is the entry fees of this attraction?",
                "answer": "Not mentioned"
            }
        ]
    },
    {
        "summary": "Veliko Tarnovo, known as the city of Tsars, is a 7000-year-old town located by the Yantra River and surrounded by three hills: Tsaravets, Trapezitsa, and Sveta Gora. The city, once the capital of the second Bulgarian empire, is walled on all sides and offers panoramic views. Attractions include Tsaravets Fortress, Monastery of the Holy Transfiguration of God, Forty Martyrs Church, and Asen's Monument.",
        "questions": [
            {
                "question": "What is the name of this attraction?",
                "answer": "Veliko Tarnovo"
            },
            {
                "question": "What are the opening hours of this attraction?",
                "answer": "Not mentioned"
            },
            {
                "question": "What is the entry fees of this attraction?",
                "answer": "Not mentioned"
            }
        ]
    },
    {
        "summary": "Bansko, a popular skiing destination in Bulgaria, is located at the foothills of the Pirin Mountains. It offers numerous ski and snowboard areas on Todorka Peak and has the longest skiing season in Bulgaria. The town is also known for its ski restaurants, nightlife, spa, and the annual Bansko Jazz Festival. Key attractions include Vihren Peak, Todorka, Kutelo, and the Bansko Gondola Ski Lift.",
        "questions": [
            {
                "question": "What is the name of this attraction?",
                "answer": "Bansko"
            },
            {
                "question": "What are the opening hours of this attraction?",
                "answer": "Not mentioned"
            },
            {
                "question": "What is the entry fees of this attraction?",
                "answer": "Not mentioned"
            }
        ]
    },
    {
        "summary": "Sozopol, an ancient coastal town in Bulgaria, showcases relics and remnants from the Bronze Age. Located on the Black Sea coast, it features an ancient fortress overlooking the sea and archaeological evidence of a sprawling Christian complex. Sozopol is known for its splendid beaches, vibrant nightlife, and as a significant cultural center hosting the Apollonia Art and Film Festival annually. Key attractions include St. Thomas Island, St. Ivan Island, and The Castle of Ravadinovo.",
        "questions": [
            {
                "question": "What is the name of this attraction?",
                "answer": "Sozopol"
            },
            {
                "question": "What are the opening hours of this attraction?",
                "answer": "Not mentioned"
            },
            {
                "question": "What is the entry fees of this attraction?",
                "answer": "Not mentioned"
            }
        ]
    },
    {
        "summary": "Koprivshtitsa is a historic town in Bulgaria known for its colorful houses, cobblestone streets, buzzing public squares, and markets. Set against the backdrop of the Sredna Gora mountains and along the Topolnita River, it is famous for its folk festivals and carnivals. Key attractions include Oslekov House, Topalova House, Dimcho Debelyanov House, and Lyuben Karavelov Museum.",
        "questions": [
            {
                "question": "What is the name of this attraction?",
                "answer": "Koprivshtitsa"
            },
            {
                "question": "What are the opening hours of this attraction?",
                "answer": "Not mentioned"
            },
            {
                "question": "What is the entry fees of this attraction?",
                "answer": "Not mentioned"
            }
        ]
    },
    {
        "summary": "Burgas, located by the sea and several lakes, is an industrial city in Bulgaria known for its beaches, restaurants, and shacks. The main promenade hosts summer theater performances, adding to the city's charm. Key attractions include the Church of Saint Cyril, Sea Garden, Lake Burgas, Lake Atanasovsko, and St. Anastasia Island.",
        "questions": [
            {
                "question": "What is the name of this attraction?",
                "answer": "Burgas"
            },
            {
                "question": "What are the opening hours of this attraction?",
                "answer": "Not mentioned"
            },
            {
                "question": "What is the entry fees of this attraction?",
                "answer": "Not mentioned"
            }
        ]
    },
    {
        "summary": "Sunny Beach is a popular destination in Bulgaria known for its nightclubs, beach shacks, restaurants, and water sports. The vibrant and dazzling beaches are a major draw for tourists. Key attractions include Action Aquapark, Winery Messembria, Sunny Beach Luna Park, and a karting track.",
        "questions": [
            {
                "question": "What is the name of this attraction?",
                "answer": "Sunny Beach"
            },
            {
                "question": "What are the opening hours of this attraction?",
                "answer": "Not mentioned"
            },
            {
                "question": "What is the entry fees of this attraction?",
                "answer": "Not mentioned"
            }
        ]
    },
    {
        "summary": "Belogradchik, located on the northern slopes of the Balkan Mountains, is famous for its unique sandstone and limestone rock formations, monoliths, and hoodoos. The area also features an ancient fort, caves, and museums. Key attractions include Magura Cave, Baba Vida, Kaleto Fortress, Belogradchik Rocks, and the Museum of Nature and Science.",
        "questions": [
            {
                "question": "What is the name of this attraction?",
                "answer": "Belogradchik"
            },
            {
                "question": "What are the opening hours of this attraction?",
                "answer": "Not mentioned"
            },
            {
                "question": "What is the entry fees of this attraction?",
                "answer": "Not mentioned"
            }
        ]
    },
    {
        "summary": "Pamporovo, a popular ski resort in Bulgaria, is located at the foothills of the Rhodope Mountains. Known for its pine forests, the area offers skiing and snowboarding in winter, and hiking and camping in summer. Key attractions include Pamporovo Ski Resort, Spree Skiing School, and Fun Park.",
        "questions": [
            {
                "question": "What is the name of this attraction?",
                "answer": "Pamporovo"
            },
            {
                "question": "What are the opening hours of this attraction?",
                "answer": "Not mentioned"
            },
            {
                "question": "What is the entry fees of this attraction?",
                "answer": "Not mentioned"
            }
        ]
    },
    {
        "summary": "Ruse, located on the right bank of the Danube, is an important river port and quaint Bulgarian city. Known as 'Little Vienna' for its architecture, the city houses over 300 buildings and features the Friendship Bridge. Key attractions include Liberty Square, Friendship Bridge, Freedom Square, Sveta Troitsa Cathedral, Eco Museum, and Orlova Chuka Cave.",
        "questions": [
            {
                "question": "What is the name of this attraction?",
                "answer": "Ruse"
            },
            {
                "question": "What are the opening hours of this attraction?",
                "answer": "Not mentioned"
            },
            {
                "question": "What is the entry fees of this attraction?",
                "answer": "Not mentioned"
            }
        ]
    },
    {
        "summary": "Hisarya, located at the edge of the Sredna Gora mountain range, is known for relics of Roman walls, gates, baths, and theaters. Situated 44 km from Plovdiv, it is a great day trip option. Key attractions include Thracian Temple, Mineral Spring, Momina Banya, and Horseback Riding Camp Ezdun.",
        "questions": [
            {
                "question": "What is the name of this attraction?",
                "answer": "Hisarya"
            },
            {
                "question": "What are the opening hours of this attraction?",
                "answer": "Not mentioned"
            },
            {
                "question": "What is the entry fees of this attraction?",
                "answer": "Not mentioned"
            }
        ]
    },
    {
        "summary": "Arbanasi, a quaint village perched on a hill about 5 kilometers from Veliko Tarnovo, offers amazing views of Veliko Tarnovo and Tsarevets. Known for its streets and old houses surrounded by high National Revival style buildings, Arbanasi is one of the oldest places in Bulgaria. Key attractions include Nativity Church and Konstantsalieva House.",
        "questions": [
            {
                "question": "What is the name of this attraction?",
                "answer": "Arbanasi"
            },
            {
                "question": "What are the opening hours of this attraction?",
                "answer": "Not mentioned"
            },
            {
                "question": "What is the entry fees of this attraction?",
                "answer": "Not mentioned"
            }
        ]
    },
    {
        "summary": "Pobiti Kamani, Bulgaria's only desert, is located 20 km west of Varna. It features sand dunes and rock formations up to 7 meters high that are hollow inside, creating a fascinating landscape. The area is home to a variety of flora and fauna. Key attractions include The Stone Forest and the Quarry in Beloslav.",
        "questions": [
            {
                "question": "What is the name of this attraction?",
                "answer": "Pobiti Kamani"
            },
            {
                "question": "What are the opening hours of this attraction?",
                "answer": "Not mentioned"
            },
            {
                "question": "What is the entry fees of this attraction?",
                "answer": "Not mentioned"
            }
        ]
    },
    {
        "summary": "Kaliakra, located along the Black Sea Coast in Bulgaria, is a historical site known for its medieval fortress and stunning backdrop. The legend tells of forty people jumping from the cliff with their hair tied together to avoid capture by the Ottomans in the 14th century. Key attractions include Cape Kaliakra and Castello di Kaliakra.",
        "questions": [
            {
                "question": "What is the name of this attraction?",
                "answer": "Kaliakra"
            },
            {
                "question": "What are the opening hours of this attraction?",
                "answer": "Not mentioned"
            },
            {
                "question": "What is the entry fees of this attraction?",
                "answer": "Not mentioned"
            }
        ]
    },
    {
        "summary": "Balchik, a popular family destination in Bulgaria, is located near the northern part of the Black Sea Coast. It features attractions such as the summer residence of Romanian Queen Marie of Edinburgh and the famous botanical gardens. Key attractions include The Palace of Balchik, Botanical Gardens, and Balchik Beach.",
        "questions": [
            {
                "question": "What is the name of this attraction?",
                "answer": "Balchik"
            },
            {
                "question": "What are the opening hours of this attraction?",
                "answer": "Not mentioned"
            },
            {
                "question": "What is the entry fees of this attraction?",
                "answer": "Not mentioned"
            }
        ]
    },
    {
        "summary": "Kazanlak, also known as the Valley of Roses, is an attractive tourist destination in Bulgaria and a UNESCO World Heritage Site. It is known for the tombstones of Thracian kings. Key attractions include the Museum of Roses, Thracian Tomb of Kazanlak, Koprinka Dam, and Tomb of Tsar Setv.",
        "questions": [
            {
                "question": "What is the name of this attraction?",
                "answer": "Kazanlak"
            },
            {
                "question": "What are the opening hours of this attraction?",
                "answer": "Not mentioned"
            },
            {
                "question": "What is the entry fees of this attraction?",
                "answer": "Not mentioned"
            }
        ]
    },
    {
        "summary": "Etara, a museum in Bulgaria, is located on the northern edge of the Bulgarka Nature Park. It displays Bulgarian customs, craftsmanship, and culture. The area also features numerous restaurants offering the finest Bulgarian cuisine. Key attractions include Karadzica and Sokolski Monastery.",
        "questions": [
            {
                "question": "What is the name of this attraction?",
                "answer": "Etara"
            },
            {
                "question": "What are the opening hours of this attraction?",
                "answer": "Not mentioned"
            },
            {
                "question": "What is the entry fees of this attraction?",
                "answer": "Not mentioned"
            }
        ]
    }
]
